ezkey/__init__.py
ezkey/ezkey.py
ezkey-0.0.1.dist-info/LICENSE
ezkey-0.0.1.dist-info/METADATA
ezkey-0.0.1.dist-info/WHEEL
ezkey-0.0.1.dist-info/top_level.txt
ezkey-0.0.1.dist-info/RECORD
