Metadata-Version: 2.1
Name: ezkey
Version: 0.0.1
Summary: ezkey is a package that allows developers to easily manage locally stored API keys.
Home-page: https://github.com/espressoAndCode/ezkey
Author: Wes Bailey
Author-email: espressoandcode@gmail.com
License: Apache 2.0
Platform: UNKNOWN
Classifier: Development Status :: 4 - Beta
Classifier: License :: OSI Approved :: Apache Software License
Classifier: Programming Language :: Python
Classifier: Topic :: Software Development :: Libraries
Classifier: Topic :: Software Development :: Libraries :: Python Modules
Classifier: Intended Audience :: Developers
Requires-Python: >=2.7
